{"ngaoyvBf6vHFcUA6Y96u5Q==":"neon%20yellow%20running%20_%20marathon%20events%20website%20(4)-1350x650.png","gvXHXvKD7NdnMYkDfFFb/A==":"neon%20yellow%20running%20_%20marathon%20events%20website%20(2)-1350x650.png","Q5OAlJbtXAAWV0oomoiqbg==":"%E4%B8%80%E9%B9%BF%E6%9C%89%E6%88%91%20%E4%B8%BA%E6%A2%A6%E6%83%B3%E5%8A%A0%E9%80%9F%20(5)-800x2000.png","cdZBK6NdReyO5Ck+d7NbVA==":"%E8%8A%B1%E5%91%97-290x290.jpg","y0J2QEMZbSp9E42wchg0Xg==":"%E7%99%BD%E6%9D%A1-256x256.png","5BNGIi1lKGk94cc2Lai+8g==":"%E7%99%BD%E6%9D%A1-256x256.png","3+iDXGu5X8IT4CW8Ff5IkQ==":"u=880475585,844468914&fm=26&gp=0-500x400.jpg","gbZsTmN3p9gsDnIXNWvc/A==":"%E4%BF%A1%E7%94%A8%E5%8D%A1-500x500.jpg","36OkV7/f54nvQVqJWiR1NQ==":"%E6%90%BA%E7%A8%8Blogo-610x610.jpg","iTmk0kw0XXiejUAhC7wMiA==":"wx20190804-154947@2x-232x234.png"}